serverless_models/__init__.py
serverless_models/db/__init__.py
serverless_models/db/init_db.py
serverless_models/db/model/__init__.py
serverless_models/db/model/base_model.py
serverless_models/db/model/domain.py
serverless_models/db/model/log.py
serverless_models/db/model/model_generator.py
serverless_models/db/model/trigger/__init__.py
serverless_models/db/model/trigger/trigger.py
serverless_models/db/model/trigger/type.py
serverless_models/db/model/user/__init__.py
serverless_models/db/model/user/function/__init__.py
serverless_models/db/model/user/function/function.py
serverless_models/db/model/user/function/tag.py
serverless_models/db/model/user/role.py
serverless_models/db/model/user/script_way.py
serverless_models/db/model/user/user.py
serverless_models/db/session.py
serverless_models/dto/__init__.py
serverless_models/dto/base.py
serverless_models/dto/domain.py
serverless_models/dto/function/__init__.py
serverless_models/dto/function/function.py
serverless_models/dto/function/tag.py
serverless_models/dto/log.py
serverless_models/dto/trigger/__init__.py
serverless_models/dto/trigger/trigger.py
serverless_models/dto/trigger/type.py
serverless_models/dto/user/__init__.py
serverless_models/dto/user/role.py
serverless_models/dto/user/script_way.py
serverless_models/dto/user/user.py
serverless_models/dto/user/workspace.py
serverless_models-0.0.2.dist-info/METADATA
serverless_models-0.0.2.dist-info/WHEEL
serverless_models-0.0.2.dist-info/RECORD
